Metadata-Version: 2.4
Name: test-classification-model-malc
Version: 0.0.5
Summary: Example classification model package from MaCh1NeT.
Home-page: https://github.com/MaCh1Ne01/deploying-machine-learning-models.git
Author: MaCh1NeT
Author-email: mluyoch01@gmail.com
License: BSD-3
Classifier: License :: OSI Approved :: MIT License
Classifier: Programming Language :: Python
Classifier: Programming Language :: Python :: 3
Classifier: Programming Language :: Python :: 3.6
Classifier: Programming Language :: Python :: 3.7
Classifier: Programming Language :: Python :: 3.8
Classifier: Programming Language :: Python :: 3.9
Classifier: Programming Language :: Python :: Implementation :: CPython
Classifier: Programming Language :: Python :: Implementation :: PyPy
Requires-Python: >=3.8.0
Requires-Dist: numpy<2.0.0,>=1.21.0
Requires-Dist: pandas==2.2.2
Requires-Dist: pydantic<2.0.0,>=1.8.1
Requires-Dist: scikit-learn<1.5.0,>=1.1.3
Requires-Dist: strictyaml<2.0.0,>=1.3.2
Requires-Dist: ruamel.yaml<1.0.0,>=0.16.12
Requires-Dist: feature-engine<1.6.0,>=1.0.2
Requires-Dist: joblib<2.0.0,>=1.0.1
Dynamic: author
Dynamic: author-email
Dynamic: classifier
Dynamic: description
Dynamic: description-content-type
Dynamic: home-page
Dynamic: license
Dynamic: requires-dist
Dynamic: requires-python
Dynamic: summary
